nicegui_admin-0.1.0.dist-info/METADATA
nicegui_admin-0.1.0.dist-info/WHEEL
nicegui_admin-0.1.0.dist-info/entry_points.txt
nicegui_admin/__init__.py
nicegui_admin/__main__.py
nicegui_admin-0.1.0.dist-info/RECORD
